{
    "description": "Adaptive high-order numerical simulations of hyperbolic PDEs in Julia",
    "license": "MIT",
    "title": "Trixi.jl",
    "upload_type": "software",
    "creators": [
        {
            "affiliation": "High-Performance Scientific Computing, University of Augsburg, Germany",
            "name": "Schlottke-Lakemper, Michael",
            "orcid": "0000-0002-3195-2536"
        },
        {
            "affiliation": "Department of Mathematics and Computer Science, University of Cologne, Germany",
            "name": "Gassner, Gregor J.",
            "orcid": "0000-0002-1752-1158"
        },
        {
            "affiliation": "Numerical Mathematics, Johannes Gutenberg University Mainz, Germany",
            "name": "Ranocha, Hendrik",
            "orcid": "0000-0002-3456-2277"
        },
        {
            "affiliation": "Department of Mathematics; Computational Mathematics, Linköping University, Sweden",
            "name": "Winters, Andrew R.",
            "orcid": "0000-0002-5902-1522"
        },
        {
            "affiliation": "Department of Computational and Applied Mathematics, Rice University, US",
            "name": "Chan, Jesse",
            "orcid": "0000-0003-2077-3636"
        }
    ],
    "access_right": "open"
}
